npdep_sourcing/__init__.py
npdep_sourcing/__main__.py
npdep_sourcing/args/Args.py
npdep_sourcing/args/__init__.py
npdep_sourcing/base/Sourcing.py
npdep_sourcing/base/__init__.py
npdep_sourcing/module/__init__.py
npdep_sourcing/module/foi/FoiModule.py
npdep_sourcing/module/foi/__init__.py
npdep_sourcing/module/rest/RestModule.py
npdep_sourcing/module/rest/__init__.py
npdep_sourcing/output/Output.py
npdep_sourcing/output/__init__.py
npdep_sourcing/util/Util.py
npdep_sourcing/util/__init__.py
npdep_sourcing-0.1.0.dist-info/METADATA
npdep_sourcing-0.1.0.dist-info/WHEEL
npdep_sourcing-0.1.0.dist-info/entry_points.txt
npdep_sourcing-0.1.0.dist-info/top_level.txt
npdep_sourcing-0.1.0.dist-info/RECORD
