Metadata-Version: 2.1
Name: npdep_sourcing
Version: 0.1.0
Summary: Sourcing Modules for Network Protocol Data Exfiltration Project Client
Home-page: https://github.com/npdep/npdep-sourcing
Author: npdep
Classifier: Operating System :: OS Independent 
Classifier: Programming Language :: Python :: 3 
Requires-Dist: foi
